netflux/__init__.py
netflux/core.py
netflux/runtime.py
netflux/assets/banner.png
netflux/demos/__init__.py
netflux/demos/apply_diff.py
netflux/demos/client_factory.py
netflux/demos/perf_opt.py
netflux/demos/puzzle.py
netflux/func_lib/__init__.py
netflux/func_lib/apply_diff.py
netflux/func_lib/bash.py
netflux/func_lib/ensemble.py
netflux/func_lib/raise_exception.py
netflux/func_lib/text_editor.py
netflux/providers/__init__.py
netflux/providers/anthropic.py
netflux/providers/gemini.py
netflux/tests/__init__.py
netflux/tests/test_agentnode.py
netflux/tests/test_arg_validation.py
netflux/tests/test_bash_function.py
netflux/tests/test_func_validation.py
netflux/tests/test_node.py
netflux/tests/test_runcontext.py
netflux/tests/test_runtime.py
netflux/tests/test_text_editor.py
netflux/viz/__init__.py
netflux/viz/console.py
netflux/viz/viz.py
netflux-0.2.8.dist-info/licenses/LICENSE
netflux-0.2.8.dist-info/METADATA
netflux-0.2.8.dist-info/WHEEL
netflux-0.2.8.dist-info/top_level.txt
netflux-0.2.8.dist-info/RECORD
