Metadata-Version: 2.4
Name: netflux
Version: 0.2.8
Summary: Framework for authoring custom agentic applications, treating agents as first-class functions.
Maintainer: LW Computational Science Research Foundation
License: MIT
Project-URL: Homepage, https://github.com/lwcsrf/netflux
Project-URL: Repository, https://github.com/lwcsrf/netflux
Project-URL: Issues, https://github.com/lwcsrf/netflux/issues
Classifier: Programming Language :: Python :: 3
Classifier: Operating System :: OS Independent
Requires-Python: >=3.9
License-File: LICENSE
Requires-Dist: overrides
Provides-Extra: test
Requires-Dist: pytest; extra == "test"
Provides-Extra: anthropic
Requires-Dist: anthropic<1.0.0,>=0.75.0; extra == "anthropic"
Requires-Dist: httpx[http2]; extra == "anthropic"
Provides-Extra: gemini
Requires-Dist: google-genai<2.0.0,>=1.56.0; extra == "gemini"
Requires-Dist: httpx[http2]; extra == "gemini"
Provides-Extra: openai
Requires-Dist: openai<2.0.0,>=1.109.1; extra == "openai"
Provides-Extra: xai
Requires-Dist: xai-sdk<2.0.0,>=1.2.0; extra == "xai"
Provides-Extra: all
Requires-Dist: netflux[test]; extra == "all"
Requires-Dist: netflux[anthropic]; extra == "all"
Requires-Dist: netflux[gemini]; extra == "all"
Requires-Dist: netflux[openai]; extra == "all"
Requires-Dist: netflux[xai]; extra == "all"
Dynamic: license-file
